odoo8_addon_web_ir_actions_act_window_none-8.0.1.0.0-py2.7-nspkg.pth
odoo_addons/web_ir_actions_act_window_none/__openerp__.py
odoo_addons/web_ir_actions_act_window_none/__init__.py
odoo_addons/web_ir_actions_act_window_none/README.rst
odoo_addons/web_ir_actions_act_window_none/views/templates.xml
odoo_addons/web_ir_actions_act_window_none/static/description/icon.png
odoo_addons/web_ir_actions_act_window_none/static/src/js/web_ir_actions_act_window_none.js
odoo8_addon_web_ir_actions_act_window_none-8.0.1.0.0.dist-info/top_level.txt
odoo8_addon_web_ir_actions_act_window_none-8.0.1.0.0.dist-info/WHEEL
odoo8_addon_web_ir_actions_act_window_none-8.0.1.0.0.dist-info/RECORD
odoo8_addon_web_ir_actions_act_window_none-8.0.1.0.0.dist-info/metadata.json
odoo8_addon_web_ir_actions_act_window_none-8.0.1.0.0.dist-info/DESCRIPTION.rst
odoo8_addon_web_ir_actions_act_window_none-8.0.1.0.0.dist-info/METADATA
odoo8_addon_web_ir_actions_act_window_none-8.0.1.0.0.dist-info/namespace_packages.txt
